azure/schemaregistry/encoder/avroencoder/__init__.py
azure/schemaregistry/encoder/avroencoder/_abstract_avro_encoder.py
azure/schemaregistry/encoder/avroencoder/_apache_avro_encoder.py
azure/schemaregistry/encoder/avroencoder/_constants.py
azure/schemaregistry/encoder/avroencoder/_exceptions.py
azure/schemaregistry/encoder/avroencoder/_message_protocol.py
azure/schemaregistry/encoder/avroencoder/_schema_registry_avro_encoder.py
azure/schemaregistry/encoder/avroencoder/_utils.py
azure/schemaregistry/encoder/avroencoder/_version.py
azure/schemaregistry/encoder/avroencoder/aio/__init__.py
azure/schemaregistry/encoder/avroencoder/aio/_async_lru.py
azure/schemaregistry/encoder/avroencoder/aio/_schema_registry_avro_encoder_async.py
azure_schemaregistry_avroencoder-1.0.0.dist-info/LICENSE
azure_schemaregistry_avroencoder-1.0.0.dist-info/METADATA
azure_schemaregistry_avroencoder-1.0.0.dist-info/WHEEL
azure_schemaregistry_avroencoder-1.0.0.dist-info/top_level.txt
azure_schemaregistry_avroencoder-1.0.0.dist-info/RECORD
