Metadata-Version: 2.1
Name: azure-schemaregistry-avroencoder
Version: 1.0.0
Summary: Microsoft Azure Schema Registry Avro Encoder Client Library for Python
Home-page: https://github.com/Azure/azure-sdk-for-python
Author: Microsoft Corporation
Author-email: azpysdkhelp@microsoft.com
License: MIT License
Platform: UNKNOWN
Classifier: Development Status :: 5 - Production/Stable
Classifier: Programming Language :: Python
Classifier: Programming Language :: Python :: 3 :: Only
Classifier: Programming Language :: Python :: 3.6
Classifier: Programming Language :: Python :: 3.7
Classifier: Programming Language :: Python :: 3.8
Classifier: Programming Language :: Python :: 3.9
Classifier: Programming Language :: Python :: 3.10
Classifier: License :: OSI Approved :: MIT License
Requires-Python: >=3.6
Requires-Dist: azure-schemaregistry (<2.0.0,>=1.0.0)
Requires-Dist: avro (>=1.11.0)
Requires-Dist: typing-extensions (>=4.0.1)
